[
    {
       "admin":[
          "/hom",
          "/home",
          "/users",
          "/user/create-user",
          "/user/edit-user/:id",
          "/plains",
          "/plains/create-plains",
          "/plains/edit-plains/:id",
          "/clients",
          "/clients/create-clients",
          "/clients/edit-clients/:id",
          "/travelers",
          "/travelers/create-travelers",
          "/travelers/edit-travelers/:id",
          "/travelers/view-travelers/:id",
          "/travelers/create-travelers/upload"
       ]
    },
    {
       "client":[
          "/hom",
          "/home",
          "/travelers",
          "/travelers/create-travelers",
          "/travelers/edit-travelers/:id",
          "/travelers/view-travelers/:id",
          "/travelers/create-travelers/upload"
       ]
    },
    {
       "consult":[
          "/hom",
          "/home",
          "/travelers"
       ]
    },
    {
       "marketing":[
          "/hom",
          "/home",
          "/clients",
          "/clients/create-clients",
          "/clients/edit-clients/:id",
          "/travelers",
          "/travelers/create-travelers",
          "/travelers/edit-travelers/:id",
          "/travelers/view-travelers/:id",
          "/travelers/create-travelers/upload"
       ]
    },
    {
       "comercial":[
          "/hom",
          "/home",
          "/plains",
          "/plains/create-plains",
          "/plains/edit-plains/:id",
          "/travelers",
          "/travelers/create-travelers",
          "/travelers/edit-travelers/:id",
          "/travelers/view-travelers/:id",
          "/travelers/create-travelers/upload"
       ]
    }
 ]